requirements.txt
setup.py
django_configurations_webpack/__init__.py
django_configurations_webpack.egg-info/PKG-INFO
django_configurations_webpack.egg-info/SOURCES.txt
django_configurations_webpack.egg-info/dependency_links.txt
django_configurations_webpack.egg-info/requires.txt
django_configurations_webpack.egg-info/top_level.txt