Metadata-Version: 2.1
Name: django-configurations-webpack
Version: 2020.7.1
Summary: django-configurations webpack settings
Home-page: https://github.com/andrewp-as-is/django-configurations-webpack.py
License: Unlicense
Keywords: django webpack configuration
Platform: UNKNOWN
Classifier: Framework :: Django
Classifier: License :: Public Domain
Classifier: Operating System :: OS Independent
Classifier: Programming Language :: Python :: 3
